setup.py
src/examples/__init__.py
src/examples/simple_client.py
src/redis_bus_python/__init__.py
src/redis_bus_python/bus_message.py
src/redis_bus_python/redis_bus.py
src/redis_bus_python/schoolbus_exceptions.py
src/redis_bus_python.egg-info/PKG-INFO
src/redis_bus_python.egg-info/SOURCES.txt
src/redis_bus_python.egg-info/dependency_links.txt
src/redis_bus_python.egg-info/requires.txt
src/redis_bus_python.egg-info/top_level.txt
src/redis_bus_python/redis_lib/__init__.py
src/redis_bus_python/redis_lib/_compat.py
src/redis_bus_python/redis_lib/client.py
src/redis_bus_python/redis_lib/connection.py
src/redis_bus_python/redis_lib/exceptions.py
src/redis_bus_python/redis_lib/lock.py
src/redis_bus_python/redis_lib/parser.py
src/redis_bus_python/redis_lib/pubsub_listener.py
src/redis_bus_python/redis_lib/sentinel.py
src/redis_bus_python/redis_lib/socket_reader.py
src/redis_bus_python/redis_lib/utils.py
src/redis_bus_python/test/__init__.py
src/redis_bus_python/test/conftest.py
src/redis_bus_python/test/performance_tests.py
src/redis_bus_python/test/sync_test_server.py
src/redis_bus_python/test/test_commands.py
src/redis_bus_python/test/test_connection.py
src/redis_bus_python/test/test_connection_pool.py
src/redis_bus_python/test/test_encoding.py
src/redis_bus_python/test/test_lock.py
src/redis_bus_python/test/test_message_delivery.py
src/redis_bus_python/test/test_oneshot_connection.py
src/redis_bus_python/test/test_pipeline.py
src/redis_bus_python/test/test_pubsub.py
src/redis_bus_python/test/test_redis_bus.py
src/redis_bus_python/test/test_scripting.py
src/redis_bus_python/test/test_sentinel.py
src/redis_bus_python/test/test_service.py
src/schoolbus_test_server/__init__.py
src/schoolbus_test_server/js_bus_bridge.py
src/schoolbus_test_server/sbtester_app_server.py
src/schoolbus_test_server/sbtester_content_server.py
src/schoolbus_test_server/schoolbus_test_server.py