Metadata-Version: 1.0
Name: redis-bus-python
Version: 0.52
Summary: Provides a software bus type API over Redis.
Home-page: https://github.com/paepcke/redis_bus_python
Author: Andreas Paepcke
Author-email: paepcke@cs.stanford.edu
License: BSD
Keywords: Redis,OpenEdX
Platform: UNKNOWN
